{
  "updated_at": "2026-07-20 15:40:08",
  "summary": {
    "stock_code": "2330",
    "stock_name": "台積電",
    "market": "twse",
    "data_source": "twse",
    "start_date": "2026-07-13",
    "end_date": "2026-07-20",
    "avg_close": 2396.67,
    "highest_price": 2480.0,
    "lowest_price": 2290.0,
    "total_volume": 288276621,
    "total_amount": 689041255420,
    "last_close": 2320.0,
    "weekly_return_pct": -4.13
  },
  "drawdown": {
    "as_of_date": "2026-07-20",
    "close": 2320.0,
    "historical_peak": 2510.0,
    "current_drawdown_pct": -7.57,
    "max_historical_drawdown_pct": -12.66
  },
  "signal": {
    "status": "看差",
    "color": "green",
    "emoji": "🟢",
    "desc": "空頭整理排列 (Close <= 5MA <= 20MA)。目前價格 TWD 2320.0，5MA(2388.0)、20MA(2423.75)。"
  },
  "extended_metrics": {
    "monthly_return_pct": -2.73,
    "quarterly_return_pct": 14.29,
    "annualized_volatility_pct": 36.14,
    "week_52_high": 2535.0,
    "week_52_low": 1740.0,
    "pct_from_52_high": -8.48,
    "pct_from_52_low": 33.33,
    "vwap": 2135.27,
    "max_consecutive_up_days": 4,
    "max_consecutive_down_days": 4,
    "support_level": 2055.0,
    "resistance_level": 2535.0,
    "volume_price_divergence": {
      "status": "價跌量增",
      "desc": "近5日價格下跌但量能擴大，可能恐慌性賣壓。"
    }
  },
  "chart_data": [
    {
      "Date": "2026-04-23",
      "Open": 2090.0,
      "High": 2135.0,
      "Low": 2055.0,
      "Close": 2080.0,
      "Volume": 54918117,
      "Amount": 114822791851,
      "Change": 30.0,
      "Transactions": 161370,
      "MA5": 2047.0,
      "MA20": 1946.0,
      "MA60": 1900.92,
      "RSI": null,
      "DIF": null,
      "MACD": null,
      "OSC": null,
      "K": null,
      "D": null,
      "ATR": null,
      "BB_Upper": null,
      "BB_Middle": null,
      "BB_Lower": null,
      "Vol_MA5": null,
      "Vol_MA20": null
    },
    {
      "Date": "2026-04-24",
      "Open": 2110.0,
      "High": 2190.0,
      "Low": 2105.0,
      "Close": 2185.0,
      "Volume": 52391785,
      "Amount": 112917570260,
      "Change": 105.0,
      "Transactions": 174859,
      "MA5": 2078.0,
      "MA20": 1963.0,
      "MA60": 1906.6,
      "RSI": null,
      "DIF": null,
      "MACD": null,
      "OSC": null,
      "K": null,
      "D": null,
      "ATR": null,
      "BB_Upper": null,
      "BB_Middle": null,
      "BB_Lower": null,
      "Vol_MA5": null,
      "Vol_MA20": null
    },
    {
      "Date": "2026-04-27",
      "Open": 2280.0,
      "High": 2330.0,
      "Low": 2265.0,
      "Close": 2265.0,
      "Volume": 79778277,
      "Amount": 183309899207,
      "Change": 80.0,
      "Transactions": 323994,
      "MA5": 2126.0,
      "MA20": 1984.25,
      "MA60": 1913.63,
      "RSI": null,
      "DIF": null,
      "MACD": null,
      "OSC": null,
      "K": null,
      "D": null,
      "ATR": null,
      "BB_Upper": null,
      "BB_Middle": null,
      "BB_Lower": null,
      "Vol_MA5": null,
      "Vol_MA20": null
    },
    {
      "Date": "2026-04-28",
      "Open": 2245.0,
      "High": 2280.0,
      "Low": 2215.0,
      "Close": 2215.0,
      "Volume": 57336004,
      "Amount": 128432565716,
      "Change": -50.0,
      "Transactions": 308514,
      "MA5": 2159.0,
      "MA20": 2004.0,
      "MA60": 1919.42,
      "RSI": null,
      "DIF": null,
      "MACD": null,
      "OSC": null,
      "K": null,
      "D": null,
      "ATR": null,
      "BB_Upper": null,
      "BB_Middle": null,
      "BB_Lower": null,
      "Vol_MA5": null,
      "Vol_MA20": null
    },
    {
      "Date": "2026-04-29",
      "Open": 2175.0,
      "High": 2210.0,
      "Low": 2165.0,
      "Close": 2180.0,
      "Volume": 49147402,
      "Amount": 107324137160,
      "Change": -35.0,
      "Transactions": 233692,
      "MA5": 2185.0,
      "MA20": 2024.0,
      "MA60": 1924.34,
      "RSI": null,
      "DIF": null,
      "MACD": null,
      "OSC": null,
      "K": null,
      "D": null,
      "ATR": null,
      "BB_Upper": null,
      "BB_Middle": null,
      "BB_Lower": null,
      "Vol_MA5": 58714317,
      "Vol_MA20": null
    },
    {
      "Date": "2026-04-30",
      "Open": 2205.0,
      "High": 2215.0,
      "Low": 2135.0,
      "Close": 2135.0,
      "Volume": 59584011,
      "Amount": 129082703075,
      "Change": -45.0,
      "Transactions": 290470,
      "MA5": 2196.0,
      "MA20": 2042.75,
      "MA60": 1928.24,
      "RSI": null,
      "DIF": null,
      "MACD": null,
      "OSC": null,
      "K": null,
      "D": null,
      "ATR": null,
      "BB_Upper": null,
      "BB_Middle": null,
      "BB_Lower": null,
      "Vol_MA5": 59647495,
      "Vol_MA20": null
    },
    {
      "Date": "2026-05-04",
      "Open": 2200.0,
      "High": 2285.0,
      "Low": 2195.0,
      "Close": 2275.0,
      "Volume": 44458732,
      "Amount": 99944198300,
      "Change": 140.0,
      "Transactions": 129173,
      "MA5": 2214.0,
      "MA20": 2063.75,
      "MA60": 1934.55,
      "RSI": null,
      "DIF": null,
      "MACD": null,
      "OSC": null,
      "K": null,
      "D": null,
      "ATR": null,
      "BB_Upper": null,
      "BB_Middle": null,
      "BB_Lower": null,
      "Vol_MA5": 58060885,
      "Vol_MA20": null
    },
    {
      "Date": "2026-05-05",
      "Open": 2250.0,
      "High": 2270.0,
      "Low": 2240.0,
      "Close": 2250.0,
      "Volume": 26644983,
      "Amount": 60009590420,
      "Change": -25.0,
      "Transactions": 153870,
      "MA5": 2211.0,
      "MA20": 2085.75,
      "MA60": 1940.18,
      "RSI": null,
      "DIF": null,
      "MACD": null,
      "OSC": null,
      "K": null,
      "D": null,
      "ATR": null,
      "BB_Upper": null,
      "BB_Middle": null,
      "BB_Lower": null,
      "Vol_MA5": 47434226,
      "Vol_MA20": null
    },
    {
      "Date": "2026-05-06",
      "Open": 2250.0,
      "High": 2285.0,
      "Low": 2240.0,
      "Close": 2250.0,
      "Volume": 38026963,
      "Amount": 85874042414,
      "Change": 0.0,
      "Transactions": 125342,
      "MA5": 2218.0,
      "MA20": 2105.25,
      "MA60": 1945.61,
      "RSI": null,
      "DIF": null,
      "MACD": null,
      "OSC": null,
      "K": 56.97,
      "D": 52.32,
      "ATR": null,
      "BB_Upper": null,
      "BB_Middle": null,
      "BB_Lower": null,
      "Vol_MA5": 43572418,
      "Vol_MA20": null
    },
    {
      "Date": "2026-05-07",
      "Open": 2335.0,
      "High": 2345.0,
      "Low": 2310.0,
      "Close": 2310.0,
      "Volume": 41966283,
      "Amount": 97374950118,
      "Change": 60.0,
      "Transactions": 127355,
      "MA5": 2244.0,
      "MA20": 2123.25,
      "MA60": 1951.9,
      "RSI": null,
      "DIF": null,
      "MACD": null,
      "OSC": null,
      "K": 66.45,
      "D": 57.03,
      "ATR": null,
      "BB_Upper": null,
      "BB_Middle": null,
      "BB_Lower": null,
      "Vol_MA5": 42136194,
      "Vol_MA20": null
    },
    {
      "Date": "2026-05-08",
      "Open": 2300.0,
      "High": 2310.0,
      "Low": 2265.0,
      "Close": 2290.0,
      "Volume": 31730352,
      "Amount": 72760055995,
      "Change": -20.0,
      "Transactions": 153342,
      "MA5": 2275.0,
      "MA20": 2140.0,
      "MA60": 1957.63,
      "RSI": null,
      "DIF": null,
      "MACD": null,
      "OSC": null,
      "K": 68.9,
      "D": 60.99,
      "ATR": null,
      "BB_Upper": null,
      "BB_Middle": null,
      "BB_Lower": null,
      "Vol_MA5": 36565462,
      "Vol_MA20": null
    },
    {
      "Date": "2026-05-11",
      "Open": 2265.0,
      "High": 2275.0,
      "Low": 2235.0,
      "Close": 2235.0,
      "Volume": 46172626,
      "Amount": 104025934565,
      "Change": -55.0,
      "Transactions": 377408,
      "MA5": 2267.0,
      "MA20": 2151.75,
      "MA60": 1962.25,
      "RSI": null,
      "DIF": null,
      "MACD": null,
      "OSC": null,
      "K": 61.81,
      "D": 61.26,
      "ATR": null,
      "BB_Upper": null,
      "BB_Middle": null,
      "BB_Lower": null,
      "Vol_MA5": 36908241,
      "Vol_MA20": null
    },
    {
      "Date": "2026-05-12",
      "Open": 2235.0,
      "High": 2280.0,
      "Low": 2210.0,
      "Close": 2255.0,
      "Volume": 54239538,
      "Amount": 121891443938,
      "Change": 20.0,
      "Transactions": 183443,
      "MA5": 2268.0,
      "MA20": 2165.0,
      "MA60": 1970.42,
      "RSI": null,
      "DIF": null,
      "MACD": null,
      "OSC": null,
      "K": 60.25,
      "D": 60.93,
      "ATR": null,
      "BB_Upper": null,
      "BB_Middle": null,
      "BB_Lower": null,
      "Vol_MA5": 42427152,
      "Vol_MA20": null
    },
    {
      "Date": "2026-05-13",
      "Open": 2205.0,
      "High": 2240.0,
      "Low": 2205.0,
      "Close": 2220.0,
      "Volume": 43727683,
      "Amount": 96933847961,
      "Change": -35.0,
      "Transactions": 259489,
      "MA5": 2262.0,
      "MA20": 2173.25,
      "MA60": 1977.42,
      "RSI": null,
      "DIF": null,
      "MACD": null,
      "OSC": null,
      "K": 53.66,
      "D": 58.5,
      "ATR": null,
      "BB_Upper": null,
      "BB_Middle": null,
      "BB_Lower": null,
      "Vol_MA5": 43567296,
      "Vol_MA20": null
    },
    {
      "Date": "2026-05-14",
      "Open": 2250.0,
      "High": 2270.0,
      "Low": 2230.0,
      "Close": 2270.0,
      "Volume": 39564699,
      "Amount": 89220307307,
      "Change": 50.0,
      "Transactions": 83872,
      "MA5": 2254.0,
      "MA20": 2182.75,
      "MA60": 1985.5,
      "RSI": 63.19,
      "DIF": null,
      "MACD": null,
      "OSC": null,
      "K": 52.44,
      "D": 56.48,
      "ATR": 74.6429,
      "BB_Upper": null,
      "BB_Middle": null,
      "BB_Lower": null,
      "Vol_MA5": 43086979,
      "Vol_MA20": null
    },
    {
      "Date": "2026-05-15",
      "Open": 2310.0,
      "High": 2325.0,
      "Low": 2250.0,
      "Close": 2265.0,
      "Volume": 34360513,
      "Amount": 78454021723,
      "Change": -5.0,
      "Transactions": 129447,
      "MA5": 2249.0,
      "MA20": 2191.75,
      "MA60": 1993.83,
      "RSI": 62.73,
      "DIF": null,
      "MACD": null,
      "OSC": null,
      "K": 49.25,
      "D": 54.07,
      "ATR": 74.6684,
      "BB_Upper": null,
      "BB_Middle": null,
      "BB_Lower": null,
      "Vol_MA5": 43613011,
      "Vol_MA20": null
    },
    {
      "Date": "2026-05-18",
      "Open": 2225.0,
      "High": 2260.0,
      "Low": 2215.0,
      "Close": 2240.0,
      "Volume": 32966937,
      "Amount": 73654895962,
      "Change": -25.0,
      "Transactions": 146159,
      "MA5": 2250.0,
      "MA20": 2202.25,
      "MA60": 2001.5,
      "RSI": 60.31,
      "DIF": null,
      "MACD": null,
      "OSC": null,
      "K": 41.16,
      "D": 49.77,
      "ATR": 72.9064,
      "BB_Upper": null,
      "BB_Middle": null,
      "BB_Lower": null,
      "Vol_MA5": 40971874,
      "Vol_MA20": null
    },
    {
      "Date": "2026-05-19",
      "Open": 2220.0,
      "High": 2230.0,
      "Low": 2205.0,
      "Close": 2205.0,
      "Volume": 45585931,
      "Amount": 100876592734,
      "Change": -35.0,
      "Transactions": 277760,
      "MA5": 2240.0,
      "MA20": 2211.25,
      "MA60": 2008.0,
      "RSI": 57.01,
      "DIF": null,
      "MACD": null,
      "OSC": null,
      "K": 27.44,
      "D": 42.33,
      "ATR": 70.1988,
      "BB_Upper": null,
      "BB_Middle": null,
      "BB_Lower": null,
      "Vol_MA5": 39241152,
      "Vol_MA20": null
    },
    {
      "Date": "2026-05-20",
      "Open": 2205.0,
      "High": 2210.0,
      "Low": 2185.0,
      "Close": 2185.0,
      "Volume": 38332945,
      "Amount": 84197244281,
      "Change": -20.0,
      "Transactions": 233768,
      "MA5": 2233.0,
      "MA20": 2218.0,
      "MA60": 2013.08,
      "RSI": 55.15,
      "DIF": null,
      "MACD": null,
      "OSC": null,
      "K": 18.3,
      "D": 34.32,
      "ATR": 66.9703,
      "BB_Upper": null,
      "BB_Middle": null,
      "BB_Lower": null,
      "Vol_MA5": 38162205,
      "Vol_MA20": null
    },
    {
      "Date": "2026-05-21",
      "Open": 2240.0,
      "High": 2255.0,
      "Low": 2230.0,
      "Close": 2230.0,
      "Volume": 24929331,
      "Amount": 55826019099,
      "Change": 45.0,
      "Transactions": 75045,
      "MA5": 2225.0,
      "MA20": 2227.0,
      "MA60": 2018.33,
      "RSI": 58.44,
      "DIF": null,
      "MACD": null,
      "OSC": null,
      "K": 22.91,
      "D": 30.51,
      "ATR": 67.1867,
      "BB_Upper": 2333.27,
      "BB_Middle": 2227.0,
      "BB_Lower": 2120.73,
      "Vol_MA5": 35235131,
      "Vol_MA20": 44793155
    },
    {
      "Date": "2026-05-22",
      "Open": 2245.0,
      "High": 2260.0,
      "Low": 2225.0,
      "Close": 2255.0,
      "Volume": 26823133,
      "Amount": 60188140377,
      "Change": 25.0,
      "Transactions": 95365,
      "MA5": 2223.0,
      "MA20": 2235.75,
      "MA60": 2024.25,
      "RSI": 60.18,
      "DIF": null,
      "MACD": null,
      "OSC": null,
      "K": 31.94,
      "D": 30.99,
      "ATR": 64.8876,
      "BB_Upper": 2318.35,
      "BB_Middle": 2235.75,
      "BB_Lower": 2153.15,
      "Vol_MA5": 33727655,
      "Vol_MA20": 43388406
    },
    {
      "Date": "2026-05-25",
      "Open": 2275.0,
      "High": 2310.0,
      "Low": 2275.0,
      "Close": 2310.0,
      "Volume": 28250944,
      "Amount": 64901118325,
      "Change": 55.0,
      "Transactions": 120043,
      "MA5": 2237.0,
      "MA20": 2242.0,
      "MA60": 2030.0,
      "RSI": 63.78,
      "DIF": null,
      "MACD": null,
      "OSC": null,
      "K": 51.06,
      "D": 37.68,
      "ATR": 64.1813,
      "BB_Upper": 2327.17,
      "BB_Middle": 2242.0,
      "BB_Lower": 2156.83,
      "Vol_MA5": 32784456,
      "Vol_MA20": 42181364
    },
    {
      "Date": "2026-05-26",
      "Open": 2320.0,
      "High": 2325.0,
      "Low": 2270.0,
      "Close": 2270.0,
      "Volume": 32781470,
      "Amount": 75166410300,
      "Change": -40.0,
      "Transactions": 203876,
      "MA5": 2250.0,
      "MA20": 2242.25,
      "MA60": 2034.25,
      "RSI": 59.56,
      "DIF": null,
      "MACD": null,
      "OSC": null,
      "K": 54.28,
      "D": 43.21,
      "ATR": 63.5255,
      "BB_Upper": 2327.72,
      "BB_Middle": 2242.25,
      "BB_Lower": 2156.78,
      "Vol_MA5": 30223564,
      "Vol_MA20": 39831524
    },
    {
      "Date": "2026-05-27",
      "Open": 2310.0,
      "High": 2330.0,
      "Low": 2290.0,
      "Close": 2300.0,
      "Volume": 40272350,
      "Amount": 93104987424,
      "Change": 30.0,
      "Transactions": 124314,
      "MA5": 2273.0,
      "MA20": 2246.5,
      "MA60": 2039.33,
      "RSI": 61.61,
      "DIF": null,
      "MACD": null,
      "OSC": null,
      "K": 62.62,
      "D": 49.68,
      "ATR": 63.2737,
      "BB_Upper": 2334.54,
      "BB_Middle": 2246.5,
      "BB_Lower": 2158.46,
      "Vol_MA5": 30611445,
      "Vol_MA20": 38978341
    },
    {
      "Date": "2026-05-28",
      "Open": 2350.0,
      "High": 2360.0,
      "Low": 2270.0,
      "Close": 2295.0,
      "Volume": 42313277,
      "Amount": 98017950283,
      "Change": -5.0,
      "Transactions": 208403,
      "MA5": 2286.0,
      "MA20": 2252.25,
      "MA60": 2044.67,
      "RSI": 61.06,
      "DIF": null,
      "MACD": null,
      "OSC": null,
      "K": 62.7,
      "D": 54.02,
      "ATR": 65.1827,
      "BB_Upper": 2337.13,
      "BB_Middle": 2252.25,
      "BB_Lower": 2167.37,
      "Vol_MA5": 34088234,
      "Vol_MA20": 38636635
    },
    {
      "Date": "2026-05-29",
      "Open": 2340.0,
      "High": 2375.0,
      "Low": 2330.0,
      "Close": 2355.0,
      "Volume": 104783831,
      "Amount": 246787941206,
      "Change": 60.0,
      "Transactions": 127095,
      "MA5": 2306.0,
      "MA20": 2263.25,
      "MA60": 2051.67,
      "RSI": 65.12,
      "DIF": 32.5212,
      "MACD": null,
      "OSC": null,
      "K": 71.62,
      "D": 59.89,
      "ATR": 66.2411,
      "BB_Upper": 2341.24,
      "BB_Middle": 2263.25,
      "BB_Lower": 2185.26,
      "Vol_MA5": 49680374,
      "Vol_MA20": 40896626
    },
    {
      "Date": "2026-06-01",
      "Open": 2355.0,
      "High": 2415.0,
      "Low": 2350.0,
      "Close": 2355.0,
      "Volume": 60942792,
      "Amount": 144105259583,
      "Change": 0.0,
      "Transactions": 136367,
      "MA5": 2315.0,
      "MA20": 2267.25,
      "MA60": 2059.83,
      "RSI": 65.12,
      "DIF": 36.4309,
      "MACD": null,
      "OSC": null,
      "K": 72.39,
      "D": 64.05,
      "ATR": 66.1525,
      "BB_Upper": 2354.86,
      "BB_Middle": 2267.25,
      "BB_Lower": 2179.64,
      "Vol_MA5": 56218744,
      "Vol_MA20": 41720829
    },
    {
      "Date": "2026-06-02",
      "Open": 2390.0,
      "High": 2400.0,
      "Low": 2360.0,
      "Close": 2380.0,
      "Volume": 41532527,
      "Amount": 98885005900,
      "Change": 25.0,
      "Transactions": 99496,
      "MA5": 2337.0,
      "MA20": 2273.75,
      "MA60": 2067.83,
      "RSI": 66.8,
      "DIF": 41.0733,
      "MACD": null,
      "OSC": null,
      "K": 75.45,
      "D": 67.85,
      "ATR": 64.6416,
      "BB_Upper": 2373.69,
      "BB_Middle": 2273.75,
      "BB_Lower": 2173.81,
      "Vol_MA5": 57968955,
      "Vol_MA20": 42465206
    },
    {
      "Date": "2026-06-03",
      "Open": 2425.0,
      "High": 2440.0,
      "Low": 2410.0,
      "Close": 2425.0,
      "Volume": 29219904,
      "Amount": 70861766012,
      "Change": 45.0,
      "Transactions": 89415,
      "MA5": 2362.0,
      "MA20": 2282.5,
      "MA60": 2076.75,
      "RSI": 69.63,
      "DIF": 47.8321,
      "MACD": null,
      "OSC": null,
      "K": 81.31,
      "D": 72.34,
      "ATR": 64.3101,
      "BB_Upper": 2401.43,
      "BB_Middle": 2282.5,
      "BB_Lower": 2163.57,
      "Vol_MA5": 55758466,
      "Vol_MA20": 42024853
    },
    {
      "Date": "2026-06-04",
      "Open": 2385.0,
      "High": 2415.0,
      "Low": 2385.0,
      "Close": 2385.0,
      "Volume": 32542948,
      "Amount": 77931338144,
      "Change": -40.0,
      "Transactions": 196886,
      "MA5": 2380.0,
      "MA20": 2286.25,
      "MA60": 2086.33,
      "RSI": 64.38,
      "DIF": 49.3914,
      "MACD": null,
      "OSC": null,
      "K": 76.75,
      "D": 73.81,
      "ATR": 62.5737,
      "BB_Upper": 2412.89,
      "BB_Middle": 2286.25,
      "BB_Lower": 2159.61,
      "Vol_MA5": 53804400,
      "Vol_MA20": 41553686
    },
    {
      "Date": "2026-06-05",
      "Open": 2395.0,
      "High": 2405.0,
      "Low": 2350.0,
      "Close": 2365.0,
      "Volume": 43403895,
      "Amount": 102970368110,
      "Change": -20.0,
      "Transactions": 364351,
      "MA5": 2382.0,
      "MA20": 2290.0,
      "MA60": 2094.92,
      "RSI": 61.87,
      "DIF": 48.4548,
      "MACD": null,
      "OSC": null,
      "K": 69.8,
      "D": 72.47,
      "ATR": 62.0327,
      "BB_Upper": 2421.22,
      "BB_Middle": 2290.0,
      "BB_Lower": 2158.78,
      "Vol_MA5": 41528413,
      "Vol_MA20": 42137363
    },
    {
      "Date": "2026-06-08",
      "Open": 2230.0,
      "High": 2320.0,
      "Low": 2230.0,
      "Close": 2295.0,
      "Volume": 52273858,
      "Amount": 119557290165,
      "Change": -70.0,
      "Transactions": 436256,
      "MA5": 2370.0,
      "MA20": 2293.0,
      "MA60": 2100.83,
      "RSI": 53.94,
      "DIF": 41.5848,
      "MACD": null,
      "OSC": null,
      "K": 56.85,
      "D": 67.26,
      "ATR": 67.2446,
      "BB_Upper": 2421.78,
      "BB_Middle": 2293.0,
      "BB_Lower": 2164.22,
      "Vol_MA5": 39794626,
      "Vol_MA20": 42442425
    },
    {
      "Date": "2026-06-09",
      "Open": 2305.0,
      "High": 2320.0,
      "Low": 2295.0,
      "Close": 2305.0,
      "Volume": 38847544,
      "Amount": 89604249837,
      "Change": 10.0,
      "Transactions": 156384,
      "MA5": 2355.0,
      "MA20": 2295.5,
      "MA60": 2107.83,
      "RSI": 54.83,
      "DIF": 36.5261,
      "MACD": null,
      "OSC": null,
      "K": 49.8,
      "D": 61.44,
      "ATR": 64.2271,
      "BB_Upper": 2423.17,
      "BB_Middle": 2295.5,
      "BB_Lower": 2167.83,
      "Vol_MA5": 39257629,
      "Vol_MA20": 41672825
    },
    {
      "Date": "2026-06-10",
      "Open": 2285.0,
      "High": 2300.0,
      "Low": 2255.0,
      "Close": 2255.0,
      "Volume": 54194021,
      "Amount": 123146622990,
      "Change": -50.0,
      "Transactions": 510491,
      "MA5": 2321.0,
      "MA20": 2297.25,
      "MA60": 2114.33,
      "RSI": 49.66,
      "DIF": 28.158,
      "MACD": 40.2192,
      "OSC": -12.0612,
      "K": 37.17,
      "D": 53.35,
      "ATR": 63.2109,
      "BB_Upper": 2421.65,
      "BB_Middle": 2297.25,
      "BB_Lower": 2172.85,
      "Vol_MA5": 44252453,
      "Vol_MA20": 42196142
    },
    {
      "Date": "2026-06-11",
      "Open": 2240.0,
      "High": 2260.0,
      "Low": 2210.0,
      "Close": 2250.0,
      "Volume": 46417523,
      "Amount": 104091484739,
      "Change": 0.0,
      "Transactions": 320151,
      "MA5": 2294.0,
      "MA20": 2296.25,
      "MA60": 2121.08,
      "RSI": 49.16,
      "DIF": 20.8819,
      "MACD": 36.3517,
      "OSC": -15.4698,
      "K": 30.58,
      "D": 45.76,
      "ATR": 62.2673,
      "BB_Upper": 2421.82,
      "BB_Middle": 2296.25,
      "BB_Lower": 2170.68,
      "Vol_MA5": 47027368,
      "Vol_MA20": 42538783
    },
    {
      "Date": "2026-06-12",
      "Open": 2325.0,
      "High": 2325.0,
      "Low": 2290.0,
      "Close": 2310.0,
      "Volume": 26306885,
      "Amount": 60666936905,
      "Change": 60.0,
      "Transactions": 77219,
      "MA5": 2283.0,
      "MA20": 2298.5,
      "MA60": 2128.42,
      "RSI": 55.0,
      "DIF": 19.7297,
      "MACD": 33.0273,
      "OSC": -13.2976,
      "K": 34.88,
      "D": 42.13,
      "ATR": 63.1768,
      "BB_Upper": 2423.36,
      "BB_Middle": 2298.5,
      "BB_Lower": 2173.64,
      "Vol_MA5": 43607966,
      "Vol_MA20": 42136102
    },
    {
      "Date": "2026-06-15",
      "Open": 2360.0,
      "High": 2375.0,
      "Low": 2345.0,
      "Close": 2375.0,
      "Volume": 30228535,
      "Amount": 71454258620,
      "Change": 65.0,
      "Transactions": 96307,
      "MA5": 2299.0,
      "MA20": 2305.25,
      "MA60": 2136.25,
      "RSI": 60.33,
      "DIF": 23.7873,
      "MACD": 31.1793,
      "OSC": -7.392,
      "K": 47.16,
      "D": 43.81,
      "ATR": 63.307,
      "BB_Upper": 2431.32,
      "BB_Middle": 2305.25,
      "BB_Lower": 2179.18,
      "Vol_MA5": 39198901,
      "Vol_MA20": 41999182
    },
    {
      "Date": "2026-06-16",
      "Open": 2375.0,
      "High": 2400.0,
      "Low": 2350.0,
      "Close": 2400.0,
      "Volume": 37145708,
      "Amount": 88421095704,
      "Change": 25.0,
      "Transactions": 99659,
      "MA5": 2318.0,
      "MA20": 2315.0,
      "MA60": 2145.42,
      "RSI": 62.18,
      "DIF": 28.6895,
      "MACD": 30.6813,
      "OSC": -1.9918,
      "K": 62.34,
      "D": 49.99,
      "ATR": 62.3565,
      "BB_Upper": 2438.69,
      "BB_Middle": 2315.0,
      "BB_Lower": 2191.31,
      "Vol_MA5": 38858534,
      "Vol_MA20": 41577171
    },
    {
      "Date": "2026-06-17",
      "Open": 2355.0,
      "High": 2385.0,
      "Low": 2350.0,
      "Close": 2385.0,
      "Volume": 30059393,
      "Amount": 71151958866,
      "Change": -15.0,
      "Transactions": 143625,
      "MA5": 2344.0,
      "MA20": 2325.0,
      "MA60": 2154.5,
      "RSI": 60.36,
      "DIF": 31.0068,
      "MACD": 30.7464,
      "OSC": 0.2604,
      "K": 71.47,
      "D": 57.15,
      "ATR": 61.4739,
      "BB_Upper": 2436.8,
      "BB_Middle": 2325.0,
      "BB_Lower": 2213.2,
      "Vol_MA5": 34031608,
      "Vol_MA20": 41163493
    },
    {
      "Date": "2026-06-18",
      "Open": 2395.0,
      "High": 2415.0,
      "Low": 2385.0,
      "Close": 2410.0,
      "Volume": 49982610,
      "Amount": 120198889493,
      "Change": 25.0,
      "Transactions": 103190,
      "MA5": 2376.0,
      "MA20": 2334.0,
      "MA60": 2164.5,
      "RSI": 62.34,
      "DIF": 34.4633,
      "MACD": 31.4898,
      "OSC": 2.9735,
      "K": 80.17,
      "D": 64.82,
      "ATR": 59.2258,
      "BB_Upper": 2442.7,
      "BB_Middle": 2334.0,
      "BB_Lower": 2225.3,
      "Vol_MA5": 34744626,
      "Vol_MA20": 42416157
    },
    {
      "Date": "2026-06-22",
      "Open": 2455.0,
      "High": 2510.0,
      "Low": 2455.0,
      "Close": 2510.0,
      "Volume": 45207883,
      "Amount": 112735082698,
      "Change": 100.0,
      "Transactions": 159770,
      "MA5": 2416.0,
      "MA20": 2346.75,
      "MA60": 2176.17,
      "RSI": 69.01,
      "DIF": 44.7558,
      "MACD": 34.143,
      "OSC": 10.6128,
      "K": 86.78,
      "D": 72.14,
      "ATR": 62.1382,
      "BB_Upper": 2473.69,
      "BB_Middle": 2346.75,
      "BB_Lower": 2219.81,
      "Vol_MA5": 38524825,
      "Vol_MA20": 43335394
    },
    {
      "Date": "2026-06-23",
      "Open": 2510.0,
      "High": 2535.0,
      "Low": 2490.0,
      "Close": 2490.0,
      "Volume": 39537895,
      "Amount": 99064704659,
      "Change": -20.0,
      "Transactions": 148609,
      "MA5": 2439.0,
      "MA20": 2355.75,
      "MA60": 2186.92,
      "RSI": 66.47,
      "DIF": 50.7143,
      "MACD": 37.4573,
      "OSC": 13.257,
      "K": 86.57,
      "D": 76.95,
      "ATR": 60.914,
      "BB_Upper": 2495.83,
      "BB_Middle": 2355.75,
      "BB_Lower": 2215.67,
      "Vol_MA5": 40386697,
      "Vol_MA20": 43899742
    },
    {
      "Date": "2026-06-24",
      "Open": 2435.0,
      "High": 2445.0,
      "Low": 2390.0,
      "Close": 2390.0,
      "Volume": 67304477,
      "Amount": 162505741547,
      "Change": -100.0,
      "Transactions": 527599,
      "MA5": 2437.0,
      "MA20": 2361.75,
      "MA60": 2196.08,
      "RSI": 55.49,
      "DIF": 46.8274,
      "MACD": 39.3313,
      "OSC": 7.4961,
      "K": 76.18,
      "D": 76.69,
      "ATR": 63.7059,
      "BB_Upper": 2496.82,
      "BB_Middle": 2361.75,
      "BB_Lower": 2226.68,
      "Vol_MA5": 46418451,
      "Vol_MA20": 45625892
    },
    {
      "Date": "2026-06-25",
      "Open": 2410.0,
      "High": 2420.0,
      "Low": 2390.0,
      "Close": 2390.0,
      "Volume": 41099957,
      "Amount": 98673938497,
      "Change": 0.0,
      "Transactions": 132387,
      "MA5": 2438.0,
      "MA20": 2366.25,
      "MA60": 2205.58,
      "RSI": 55.49,
      "DIF": 43.2485,
      "MACD": 40.1147,
      "OSC": 3.1338,
      "K": 64.39,
      "D": 72.59,
      "ATR": 61.2983,
      "BB_Upper": 2498.76,
      "BB_Middle": 2366.25,
      "BB_Lower": 2233.74,
      "Vol_MA5": 48626564,
      "Vol_MA20": 45667273
    },
    {
      "Date": "2026-06-26",
      "Open": 2360.0,
      "High": 2370.0,
      "Low": 2325.0,
      "Close": 2340.0,
      "Volume": 53800344,
      "Amount": 126177715258,
      "Change": -50.0,
      "Transactions": 464927,
      "MA5": 2424.0,
      "MA20": 2368.5,
      "MA60": 2214.92,
      "RSI": 50.64,
      "DIF": 35.9631,
      "MACD": 39.2844,
      "OSC": -3.3213,
      "K": 45.31,
      "D": 63.5,
      "ATR": 61.5627,
      "BB_Upper": 2497.58,
      "BB_Middle": 2368.5,
      "BB_Lower": 2239.42,
      "Vol_MA5": 49390111,
      "Vol_MA20": 46241626
    },
    {
      "Date": "2026-06-29",
      "Open": 2330.0,
      "High": 2395.0,
      "Low": 2330.0,
      "Close": 2370.0,
      "Volume": 38133782,
      "Amount": 90337385683,
      "Change": 30.0,
      "Transactions": 93276,
      "MA5": 2396.0,
      "MA20": 2369.25,
      "MA60": 2225.08,
      "RSI": 53.28,
      "DIF": 32.2385,
      "MACD": 37.8752,
      "OSC": -5.6367,
      "K": 37.35,
      "D": 54.78,
      "ATR": 61.8082,
      "BB_Upper": 2498.18,
      "BB_Middle": 2369.25,
      "BB_Lower": 2240.32,
      "Vol_MA5": 47975291,
      "Vol_MA20": 42909124
    },
    {
      "Date": "2026-06-30",
      "Open": 2440.0,
      "High": 2475.0,
      "Low": 2410.0,
      "Close": 2410.0,
      "Volume": 49540227,
      "Amount": 120516271220,
      "Change": 40.0,
      "Transactions": 104582,
      "MA5": 2380.0,
      "MA20": 2372.0,
      "MA60": 2234.33,
      "RSI": 56.61,
      "DIF": 32.1438,
      "MACD": 36.7289,
      "OSC": -4.5851,
      "K": 38.39,
      "D": 49.32,
      "ATR": 64.8933,
      "BB_Upper": 2501.94,
      "BB_Middle": 2372.0,
      "BB_Lower": 2242.06,
      "Vol_MA5": 49975757,
      "Vol_MA20": 42338995
    },
    {
      "Date": "2026-07-01",
      "Open": 2495.0,
      "High": 2505.0,
      "Low": 2475.0,
      "Close": 2505.0,
      "Volume": 37544470,
      "Amount": 93600076825,
      "Change": 95.0,
      "Transactions": 111091,
      "MA5": 2403.0,
      "MA20": 2378.25,
      "MA60": 2245.92,
      "RSI": 63.3,
      "DIF": 39.2816,
      "MACD": 37.2394,
      "OSC": 2.0422,
      "K": 54.17,
      "D": 50.93,
      "ATR": 67.0438,
      "BB_Upper": 2520.56,
      "BB_Middle": 2378.25,
      "BB_Lower": 2235.94,
      "Vol_MA5": 44023756,
      "Vol_MA20": 42139592
    },
    {
      "Date": "2026-07-02",
      "Open": 2450.0,
      "High": 2480.0,
      "Low": 2445.0,
      "Close": 2465.0,
      "Volume": 35919290,
      "Amount": 88369879773,
      "Change": -40.0,
      "Transactions": 132697,
      "MA5": 2418.0,
      "MA20": 2380.25,
      "MA60": 2256.0,
      "RSI": 59.17,
      "DIF": 41.2354,
      "MACD": 38.0386,
      "OSC": 3.1968,
      "K": 58.33,
      "D": 53.4,
      "ATR": 66.5407,
      "BB_Upper": 2526.21,
      "BB_Middle": 2380.25,
      "BB_Lower": 2234.29,
      "Vol_MA5": 42987622,
      "Vol_MA20": 42474562
    },
    {
      "Date": "2026-07-03",
      "Open": 2415.0,
      "High": 2465.0,
      "Low": 2415.0,
      "Close": 2445.0,
      "Volume": 32905868,
      "Amount": 80082636340,
      "Change": -20.0,
      "Transactions": 154750,
      "MA5": 2439.0,
      "MA20": 2383.25,
      "MA60": 2264.25,
      "RSI": 57.15,
      "DIF": 40.7008,
      "MACD": 38.571,
      "OSC": 2.1298,
      "K": 57.94,
      "D": 54.91,
      "ATR": 65.3592,
      "BB_Upper": 2531.92,
      "BB_Middle": 2383.25,
      "BB_Lower": 2234.58,
      "Vol_MA5": 38808727,
      "Vol_MA20": 42492708
    },
    {
      "Date": "2026-07-06",
      "Open": 2465.0,
      "High": 2500.0,
      "Low": 2455.0,
      "Close": 2460.0,
      "Volume": 21041918,
      "Amount": 52022654454,
      "Change": 15.0,
      "Transactions": 80246,
      "MA5": 2457.0,
      "MA20": 2388.0,
      "MA60": 2272.67,
      "RSI": 58.3,
      "DIF": 41.0147,
      "MACD": 39.0597,
      "OSC": 1.955,
      "K": 63.62,
      "D": 57.82,
      "ATR": 64.6193,
      "BB_Upper": 2540.07,
      "BB_Middle": 2388.0,
      "BB_Lower": 2235.93,
      "Vol_MA5": 35390354,
      "Vol_MA20": 41374609
    },
    {
      "Date": "2026-07-07",
      "Open": 2480.0,
      "High": 2500.0,
      "Low": 2440.0,
      "Close": 2440.0,
      "Volume": 31400854,
      "Amount": 77617188273,
      "Change": -20.0,
      "Transactions": 132943,
      "MA5": 2463.0,
      "MA20": 2395.25,
      "MA60": 2280.0,
      "RSI": 56.14,
      "DIF": 39.1978,
      "MACD": 39.0873,
      "OSC": 0.1105,
      "K": 63.71,
      "D": 59.78,
      "ATR": 64.2893,
      "BB_Upper": 2542.64,
      "BB_Middle": 2395.25,
      "BB_Lower": 2247.86,
      "Vol_MA5": 31762480,
      "Vol_MA20": 40330959
    },
    {
      "Date": "2026-07-08",
      "Open": 2445.0,
      "High": 2465.0,
      "Low": 2420.0,
      "Close": 2465.0,
      "Volume": 25519599,
      "Amount": 62400639776,
      "Change": 25.0,
      "Transactions": 94688,
      "MA5": 2455.0,
      "MA20": 2403.25,
      "MA60": 2287.92,
      "RSI": 58.22,
      "DIF": 39.3219,
      "MACD": 39.1342,
      "OSC": 0.1877,
      "K": 68.4,
      "D": 62.65,
      "ATR": 62.9115,
      "BB_Upper": 2547.52,
      "BB_Middle": 2403.25,
      "BB_Lower": 2258.98,
      "Vol_MA5": 29357505,
      "Vol_MA20": 39664561
    },
    {
      "Date": "2026-07-09",
      "Open": 2450.0,
      "High": 2460.0,
      "Low": 2415.0,
      "Close": 2415.0,
      "Volume": 34681018,
      "Amount": 84397735035,
      "Change": -50.0,
      "Transactions": 201698,
      "MA5": 2445.0,
      "MA20": 2411.25,
      "MA60": 2293.92,
      "RSI": 52.83,
      "DIF": 34.9824,
      "MACD": 38.3038,
      "OSC": -3.3214,
      "K": 61.79,
      "D": 62.37,
      "ATR": 61.9892,
      "BB_Upper": 2538.49,
      "BB_Middle": 2411.25,
      "BB_Lower": 2284.01,
      "Vol_MA5": 29109851,
      "Vol_MA20": 38688911
    },
    {
      "Date": "2026-07-13",
      "Open": 2460.0,
      "High": 2480.0,
      "Low": 2440.0,
      "Close": 2440.0,
      "Volume": 35310380,
      "Amount": 86697387632,
      "Change": 25.0,
      "Transactions": 94215,
      "MA5": 2444.0,
      "MA20": 2420.75,
      "MA60": 2299.92,
      "RSI": 55.07,
      "DIF": 33.1782,
      "MACD": 37.2787,
      "OSC": -4.1005,
      "K": 51.72,
      "D": 58.82,
      "ATR": 62.2043,
      "BB_Upper": 2524.64,
      "BB_Middle": 2420.75,
      "BB_Lower": 2316.86,
      "Vol_MA5": 29590753,
      "Vol_MA20": 38133554
    },
    {
      "Date": "2026-07-14",
      "Open": 2410.0,
      "High": 2430.0,
      "Low": 2390.0,
      "Close": 2420.0,
      "Volume": 42857055,
      "Amount": 103370532441,
      "Change": -20.0,
      "Transactions": 275423,
      "MA5": 2436.0,
      "MA20": 2426.25,
      "MA60": 2305.5,
      "RSI": 52.91,
      "DIF": 29.791,
      "MACD": 35.7812,
      "OSC": -5.9902,
      "K": 43.18,
      "D": 53.6,
      "ATR": 61.3326,
      "BB_Upper": 2516.91,
      "BB_Middle": 2426.25,
      "BB_Lower": 2335.59,
      "Vol_MA5": 33953781,
      "Vol_MA20": 38961063
    },
    {
      "Date": "2026-07-15",
      "Open": 2425.0,
      "High": 2460.0,
      "Low": 2415.0,
      "Close": 2440.0,
      "Volume": 33665566,
      "Amount": 82213791038,
      "Change": 20.0,
      "Transactions": 79059,
      "MA5": 2436.0,
      "MA20": 2429.5,
      "MA60": 2312.33,
      "RSI": 54.82,
      "DIF": 28.3933,
      "MACD": 34.3036,
      "OSC": -5.9103,
      "K": 43.94,
      "D": 50.38,
      "ATR": 60.166,
      "BB_Upper": 2517.19,
      "BB_Middle": 2429.5,
      "BB_Lower": 2341.81,
      "Vol_MA5": 34406723,
      "Vol_MA20": 39132914
    },
    {
      "Date": "2026-07-16",
      "Open": 2430.0,
      "High": 2470.0,
      "Low": 2420.0,
      "Close": 2470.0,
      "Volume": 30538604,
      "Amount": 74750491934,
      "Change": 30.0,
      "Transactions": 97957,
      "MA5": 2437.0,
      "MA20": 2433.0,
      "MA60": 2319.75,
      "RSI": 57.6,
      "DIF": 29.3678,
      "MACD": 33.3164,
      "OSC": -3.9486,
      "K": 53.53,
      "D": 51.43,
      "ATR": 59.4399,
      "BB_Upper": 2521.28,
      "BB_Middle": 2433.0,
      "BB_Lower": 2344.72,
      "Vol_MA5": 35410524,
      "Vol_MA20": 38802559
    },
    {
      "Date": "2026-07-17",
      "Open": 2375.0,
      "High": 2395.0,
      "Low": 2290.0,
      "Close": 2290.0,
      "Volume": 97362670,
      "Amount": 229051751965,
      "Change": -180.0,
      "Transactions": 1150086,
      "MA5": 2412.0,
      "MA20": 2428.25,
      "MA60": 2323.75,
      "RSI": 41.21,
      "DIF": 15.4376,
      "MACD": 29.7406,
      "OSC": -14.303,
      "K": 35.69,
      "D": 46.18,
      "ATR": 68.0513,
      "BB_Upper": 2534.71,
      "BB_Middle": 2428.25,
      "BB_Lower": 2321.79,
      "Vol_MA5": 47946855,
      "Vol_MA20": 42167723
    },
    {
      "Date": "2026-07-20",
      "Open": 2300.0,
      "High": 2345.0,
      "Low": 2300.0,
      "Close": 2320.0,
      "Volume": 48542346,
      "Amount": 112957300410,
      "Change": 30.0,
      "Transactions": 188445,
      "MA5": 2388.0,
      "MA20": 2423.75,
      "MA60": 2328.25,
      "RSI": 44.06,
      "DIF": 6.7409,
      "MACD": 25.1407,
      "OSC": -18.3998,
      "K": 28.55,
      "D": 40.31,
      "ATR": 67.1191,
      "BB_Upper": 2540.06,
      "BB_Middle": 2423.75,
      "BB_Lower": 2307.44,
      "Vol_MA5": 50593248,
      "Vol_MA20": 42095710
    }
  ]
}